Workbook

Sheet Test Summary
A1: Test summary: vendor payment review (fictional case)
A3: # | B3: Test | C3: Rationale | D3: Payments flagged | E3: Amount flagged (INR) | F3: % of total spend
A4: 1 | B4: Near approval threshold | C4: Possible splitting to avoid dual approval | D4: =SUM(Payments!J2:J49) -> 10 | E4: =SUMIF(Payments!J2:J49,1,Payments!F2:F49) -> 4984000 | F4: =E4/$E$11 -> 0.42652324
A5: 2 | B5: Round-number payments | C5: Estimated or invented amounts, not invoice-driven | D5: =SUM(Payments!K2:K49) -> 5 | E5: =SUMIF(Payments!K2:K49,1,Payments!F2:F49) -> 1450000 | F5: =E5/$E$11 -> 0.12408882
A6: 3 | B6: Weekend payments | C6: Unusual timing, possible bypass of normal controls | D6: =SUM(Payments!L2:L49) -> 17 | E6: =SUMIF(Payments!L2:L49,1,Payments!F2:F49) -> 5834891 | F6: =E6/$E$11 -> 0.49934122
A7: 4 | B7: Duplicate invoice numbers (all occurrences) | C7: Possible duplicate payment | D7: =SUM(Payments!M2:M49) -> 2 | E7: =SUMIF(Payments!M2:M49,1,Payments!F2:F49) -> 624900 | F7: =E7/$E$11 -> 0.053478004
A8: 5 | B8: Offshore bank account | C8: Payee outside home country, higher bribery and laundering risk | D8: =SUM(Payments!O2:O49) -> 10 | E8: =SUMIF(Payments!O2:O49,1,Payments!F2:F49) -> 4984000 | F8: =E8/$E$11 -> 0.42652324
A9: 6 | B9: Duplicate overpayment (repeat occurrences only) | C9: Cash actually overpaid | D9: =SUM(Payments!N2:N49) -> 1 | E9: =SUMIF(Payments!N2:N49,1,Payments!F2:F49) -> 312450 | F9: =E9/$E$11 -> 0.026739002
B11: Total spend reviewed | D11: =COUNTA(Payments!A2:A49) -> 48 | E11: =SUM(Payments!F2:F49) -> 11685178
B12: Payments with 2+ flags | D12: =COUNTIF(Payments!P2:P49,">=2") -> 10 | E12: =SUMIF(Payments!P2:P49,">=2",Payments!F2:F49) -> 4984000 | F12: =E12/E11 -> 0.42652324
B14: Note: flags are red flags for follow-up, not proof of wrongdoing. Parameters are on the Assumptions sheet.

Sheet Assumptions
A1: Test parameters (fictional case: Meridian Components Pvt Ltd)
A3: Parameter | B3: Value | C3: Basis
A4: Dual-approval threshold (INR) | B4: 500000 | C4: Assumed internal policy for this case study
A5: Near-threshold band (fraction below limit) | B5: 0.02 | C5: Payments within 2% below the limit are flagged (analyst judgement)
A6: Round-number test divisor (INR) | B6: 50000 | C6: Amounts divisible by this are flagged (analyst judgement)
A7: Home bank country code | B7: IN | C7: Any other country is flagged as offshore
A9: Blue text on yellow = editable inputs. All data in this workbook is fictional.

Sheet Payments
A1: Txn ID | B1: Pay date | C1: Vendor | D1: Invoice no. | E1: Description | F1: Amount (INR) | G1: Approvals | H1: Bank country | I1: Weekday | J1: Near threshold | K1: Round number | L1: Weekend | M1: Duplicate invoice | N1: Repeat payment | O1: Offshore | P1: Flags (count)
A2: T001 | B2: 45662 | C2: Coastal Freight Carriers | D2: COA/01/664 | E2: Domestic freight | F2: 109212 | G2: 1 | H2: IN | I2: =TEXT(B2,"ddd") -> Sun | J2: =IF(AND(F2>=Assumptions!$B$4*(1-Assumptions!$B$5),F2<Assumptions!$B$4),1,0) -> 0 | K2: =IF(MOD(F2,Assumptions!$B$6)=0,1,0) -> 0 | L2: =IF(WEEKDAY(B2,2)>5,1,0) -> 1 | M2: =IF(COUNTIF($D$2:$D$49,D2)>1,1,0) -> 0 | N2: =IF(COUNTIF($D$2:D2,D2)>1,1,0) -> 0 | O2: =IF(H2<>Assumptions!$B$7,1,0) -> 0 | P2: =SUM(J2:M2)+O2 -> 1
A3: T002 | B3: 45665 | C3: Kaveri Packaging Pvt Ltd | D3: KAV/01/149 | E3: Packaging material | F3: 160884 | G3: 1 | H3: IN | I3: =TEXT(B3,"ddd") -> Wed | J3: =IF(AND(F3>=Assumptions!$B$4*(1-Assumptions!$B$5),F3<Assumptions!$B$4),1,0) -> 0 | K3: =IF(MOD(F3,Assumptions!$B$6)=0,1,0) -> 0 | L3: =IF(WEEKDAY(B3,2)>5,1,0) -> 0 | M3: =IF(COUNTIF($D$2:$D$49,D3)>1,1,0) -> 0 | N3: =IF(COUNTIF($D$2:D3,D3)>1,1,0) -> 0 | O3: =IF(H3<>Assumptions!$B$7,1,0) -> 0 | P3: =SUM(J3:M3)+O3 -> 0
A4: T003 | B4: 45675 | C4: Sterling Marine Consultants LLC | D4: SMC-101 | E4: Consulting services - port liaison | F4: 498000 | G4: 1 | H4: AE | I4: =TEXT(B4,"ddd") -> Sat | J4: =IF(AND(F4>=Assumptions!$B$4*(1-Assumptions!$B$5),F4<Assumptions!$B$4),1,0) -> 1 | K4: =IF(MOD(F4,Assumptions!$B$6)=0,1,0) -> 0 | L4: =IF(WEEKDAY(B4,2)>5,1,0) -> 1 | M4: =IF(COUNTIF($D$2:$D$49,D4)>1,1,0) -> 0 | N4: =IF(COUNTIF($D$2:D4,D4)>1,1,0) -> 0 | O4: =IF(H4<>Assumptions!$B$7,1,0) -> 1 | P4: =SUM(J4:M4)+O4 -> 3
A5: T004 | B5: 45679 | C5: Southern Steel Traders | D5: SOU/01/696 | E5: Steel sheets | F5: 188547 | G5: 1 | H5: IN | I5: =TEXT(B5,"ddd") -> Wed | J5: =IF(AND(F5>=Assumptions!$B$4*(1-Assumptions!$B$5),F5<Assumptions!$B$4),1,0) -> 0 | K5: =IF(MOD(F5,Assumptions!$B$6)=0,1,0) -> 0 | L5: =IF(WEEKDAY(B5,2)>5,1,0) -> 0 | M5: =IF(COUNTIF($D$2:$D$49,D5)>1,1,0) -> 0 | N5: =IF(COUNTIF($D$2:D5,D5)>1,1,0) -> 0 | O5: =IF(H5<>Assumptions!$B$7,1,0) -> 0 | P5: =SUM(J5:M5)+O5 -> 0
A6: T005 | B6: 45679 | C6: Brightline IT Services | D6: BRI/01/188 | E6: IT support | F6: 66905 | G6: 1 | H6: IN | I6: =TEXT(B6,"ddd") -> Wed | J6: =IF(AND(F6>=Assumptions!$B$4*(1-Assumptions!$B$5),F6<Assumptions!$B$4),1,0) -> 0 | K6: =IF(MOD(F6,Assumptions!$B$6)=0,1,0) -> 0 | L6: =IF(WEEKDAY(B6,2)>5,1,0) -> 0 | M6: =IF(COUNTIF($D$2:$D$49,D6)>1,1,0) -> 0 | N6: =IF(COUNTIF($D$2:D6,D6)>1,1,0) -> 0 | O6: =IF(H6<>Assumptions!$B$7,1,0) -> 0 | P6: =SUM(J6:M6)+O6 -> 0
A7: T006 | B7: 45698 | C7: Orion Clearance Associates | D7: OCA-20 | E7: Clearance and facilitation charges | F7: 250000 | G7: 1 | H7: IN | I7: =TEXT(B7,"ddd") -> Mon | J7: =IF(AND(F7>=Assumptions!$B$4*(1-Assumptions!$B$5),F7<Assumptions!$B$4),1,0) -> 0 | K7: =IF(MOD(F7,Assumptions!$B$6)=0,1,0) -> 1 | L7: =IF(WEEKDAY(B7,2)>5,1,0) -> 0 | M7: =IF(COUNTIF($D$2:$D$49,D7)>1,1,0) -> 0 | N7: =IF(COUNTIF($D$2:D7,D7)>1,1,0) -> 0 | O7: =IF(H7<>Assumptions!$B$7,1,0) -> 0 | P7: =SUM(J7:M7)+O7 -> 1
A8: T007 | B8: 45710 | C8: Sterling Marine Consultants LLC | D8: SMC-102 | E8: Consulting services - port liaison | F8: 497500 | G8: 1 | H8: AE | I8: =TEXT(B8,"ddd") -> Sat | J8: =IF(AND(F8>=Assumptions!$B$4*(1-Assumptions!$B$5),F8<Assumptions!$B$4),1,0) -> 1 | K8: =IF(MOD(F8,Assumptions!$B$6)=0,1,0) -> 0 | L8: =IF(WEEKDAY(B8,2)>5,1,0) -> 1 | M8: =IF(COUNTIF($D$2:$D$49,D8)>1,1,0) -> 0 | N8: =IF(COUNTIF($D$2:D8,D8)>1,1,0) -> 0 | O8: =IF(H8<>Assumptions!$B$7,1,0) -> 1 | P8: =SUM(J8:M8)+O8 -> 3
A9: T008 | B9: 45712 | C9: Kaveri Packaging Pvt Ltd | D9: KAV/02/745 | E9: Packaging material | F9: 105329 | G9: 1 | H9: IN | I9: =TEXT(B9,"ddd") -> Mon | J9: =IF(AND(F9>=Assumptions!$B$4*(1-Assumptions!$B$5),F9<Assumptions!$B$4),1,0) -> 0 | K9: =IF(MOD(F9,Assumptions!$B$6)=0,1,0) -> 0 | L9: =IF(WEEKDAY(B9,2)>5,1,0) -> 0 | M9: =IF(COUNTIF($D$2:$D$49,D9)>1,1,0) -> 0 | N9: =IF(COUNTIF($D$2:D9,D9)>1,1,0) -> 0 | O9: =IF(H9<>Assumptions!$B$7,1,0) -> 0 | P9: =SUM(J9:M9)+O9 -> 0
A10: T009 | B10: 45726 | C10: Kaveri Packaging Pvt Ltd | D10: KAV/03/979 | E10: Packaging material | F10: 89572 | G10: 1 | H10: IN | I10: =TEXT(B10,"ddd") -> Mon | J10: =IF(AND(F10>=Assumptions!$B$4*(1-Assumptions!$B$5),F10<Assumptions!$B$4),1,0) -> 0 | K10: =IF(MOD(F10,Assumptions!$B$6)=0,1,0) -> 0 | L10: =IF(WEEKDAY(B10,2)>5,1,0) -> 0 | M10: =IF(COUNTIF($D$2:$D$49,D10)>1,1,0) -> 0 | N10: =IF(COUNTIF($D$2:D10,D10)>1,1,0) -> 0 | O10: =IF(H10<>Assumptions!$B$7,1,0) -> 0 | P10: =SUM(J10:M10)+O10 -> 0
A11: T010 | B11: 45731 | C11: Sterling Marine Consultants LLC | D11: SMC-103 | E11: Consulting services - port liaison | F11: 499000 | G11: 1 | H11: AE | I11: =TEXT(B11,"ddd") -> Sat | J11: =IF(AND(F11>=Assumptions!$B$4*(1-Assumptions!$B$5),F11<Assumptions!$B$4),1,0) -> 1 | K11: =IF(MOD(F11,Assumptions!$B$6)=0,1,0) -> 0 | L11: =IF(WEEKDAY(B11,2)>5,1,0) -> 1 | M11: =IF(COUNTIF($D$2:$D$49,D11)>1,1,0) -> 0 | N11: =IF(COUNTIF($D$2:D11,D11)>1,1,0) -> 0 | O11: =IF(H11<>Assumptions!$B$7,1,0) -> 1 | P11: =SUM(J11:M11)+O11 -> 3
A12: T011 | B12: 45733 | C12: Southern Steel Traders | D12: SOU/03/220 | E12: Steel sheets | F12: 209070 | G12: 1 | H12: IN | I12: =TEXT(B12,"ddd") -> Mon | J12: =IF(AND(F12>=Assumptions!$B$4*(1-Assumptions!$B$5),F12<Assumptions!$B$4),1,0) -> 0 | K12: =IF(MOD(F12,Assumptions!$B$6)=0,1,0) -> 0 | L12: =IF(WEEKDAY(B12,2)>5,1,0) -> 0 | M12: =IF(COUNTIF($D$2:$D$49,D12)>1,1,0) -> 0 | N12: =IF(COUNTIF($D$2:D12,D12)>1,1,0) -> 0 | O12: =IF(H12<>Assumptions!$B$7,1,0) -> 0 | P12: =SUM(J12:M12)+O12 -> 0
A13: T012 | B13: 45752 | C13: Brightline IT Services | D13: BRI/04/733 | E13: IT support | F13: 102708 | G13: 1 | H13: IN | I13: =TEXT(B13,"ddd") -> Sat | J13: =IF(AND(F13>=Assumptions!$B$4*(1-Assumptions!$B$5),F13<Assumptions!$B$4),1,0) -> 0 | K13: =IF(MOD(F13,Assumptions!$B$6)=0,1,0) -> 0 | L13: =IF(WEEKDAY(B13,2)>5,1,0) -> 1 | M13: =IF(COUNTIF($D$2:$D$49,D13)>1,1,0) -> 0 | N13: =IF(COUNTIF($D$2:D13,D13)>1,1,0) -> 0 | O13: =IF(H13<>Assumptions!$B$7,1,0) -> 0 | P13: =SUM(J13:M13)+O13 -> 1
... A49: T048 | B49: 46017 | C49: Coastal Freight Carriers | D49: COA/12/507 | E49: Domestic freight | F49: 174551 | G49: 1 | H49: IN | I49: =TEXT(B49,"ddd") -> Fri | J49: =IF(AND(F49>=Assumptions!$B$4*(1-Assumptions!$B$5),F49<Assumptions!$B$4),1,0) -> 0 | K49: =IF(MOD(F49,Assumptions!$B$6)=0,1,0) -> 0 | L49: =IF(WEEKDAY(B49,2)>5,1,0) -> 0 | M49: =IF(COUNTIF($D$2:$D$49,D49)>1,1,0) -> 0 | N49: =IF(COUNTIF($D$2:D49,D49)>1,1,0) -> 0 | O49: =IF(H49<>Assumptions!$B$7,1,0) -> 0 | P49: =SUM(J49:M49)+O49 -> 0

Sheet Vendor Master
A1: Vendor | B1: Created | C1: Address / notes | D1: Bank country | E1: Onboarded by | F1: First payment | G1: Days to first payment | H1: Payments | I1: Total (INR) | J1: Share of spend | K1: Flags (sum)
A2: Kaveri Packaging Pvt Ltd | B2: 43557 | C2: Kollam industrial estate | D2: IN | E2: Procurement committee | F2: =_xlfn.MINIFS(Payments!$B$2:$B$49,Payments!$C$2:$C$49,A2) -> 45665 | G2: =F2-B2 -> 2108 | H2: =COUNTIF(Payments!$C$2:$C$49,A2) -> 10 | I2: =SUMIF(Payments!$C$2:$C$49,A2,Payments!$F$2:$F$49) -> 1464949 | J2: =I2/$I$9 -> 0.12536814 | K2: =SUMIF(Payments!$C$2:$C$49,A2,Payments!$P$2:$P$49) -> 2
A3: Southern Steel Traders | B3: 43326 | C3: Coimbatore | D3: IN | E3: Procurement committee | F3: =_xlfn.MINIFS(Payments!$B$2:$B$49,Payments!$C$2:$C$49,A3) -> 45679 | G3: =F3-B3 -> 2353 | H3: =COUNTIF(Payments!$C$2:$C$49,A3) -> 9 | I3: =SUMIF(Payments!$C$2:$C$49,A3,Payments!$F$2:$F$49) -> 2314348 | J3: =I3/$I$9 -> 0.19805843 | K3: =SUMIF(Payments!$C$2:$C$49,A3,Payments!$P$2:$P$49) -> 2
A4: Brightline IT Services | B4: 44207 | C4: Kochi | D4: IN | E4: Procurement committee | F4: =_xlfn.MINIFS(Payments!$B$2:$B$49,Payments!$C$2:$C$49,A4) -> 45679 | G4: =F4-B4 -> 1472 | H4: =COUNTIF(Payments!$C$2:$C$49,A4) -> 7 | I4: =SUMIF(Payments!$C$2:$C$49,A4,Payments!$F$2:$F$49) -> 601222 | J4: =I4/$I$9 -> 0.051451677 | K4: =SUMIF(Payments!$C$2:$C$49,A4,Payments!$P$2:$P$49) -> 3
A5: Coastal Freight Carriers | B5: 42916 | C5: Kollam port road | D5: IN | E5: Procurement committee | F5: =_xlfn.MINIFS(Payments!$B$2:$B$49,Payments!$C$2:$C$49,A5) -> 45662 | G5: =F5-B5 -> 2746 | H5: =COUNTIF(Payments!$C$2:$C$49,A5) -> 6 | I5: =SUMIF(Payments!$C$2:$C$49,A5,Payments!$F$2:$F$49) -> 685659 | J5: =I5/$I$9 -> 0.058677668 | K5: =SUMIF(Payments!$C$2:$C$49,A5,Payments!$P$2:$P$49) -> 2
A6: Sterling Marine Consultants LLC | B6: 45646 | C6: Free-zone address; no website; same contact number as employee E-014 | D6: AE | E6: E-014 (Procurement Manager) only | F6: =_xlfn.MINIFS(Payments!$B$2:$B$49,Payments!$C$2:$C$49,A6) -> 45675 | G6: =F6-B6 -> 29 | H6: =COUNTIF(Payments!$C$2:$C$49,A6) -> 10 | I6: =SUMIF(Payments!$C$2:$C$49,A6,Payments!$F$2:$F$49) -> 4984000 | J6: =I6/$I$9 -> 0.42652324 | K6: =SUMIF(Payments!$C$2:$C$49,A6,Payments!$P$2:$P$49) -> 30
A7: Orion Clearance Associates | B7: 45654 | C7: Residential address; no GST on early invoices | D7: IN | E7: E-014 (Procurement Manager) only | F7: =_xlfn.MINIFS(Payments!$B$2:$B$49,Payments!$C$2:$C$49,A7) -> 45698 | G7: =F7-B7 -> 44 | H7: =COUNTIF(Payments!$C$2:$C$49,A7) -> 5 | I7: =SUMIF(Payments!$C$2:$C$49,A7,Payments!$F$2:$F$49) -> 1450000 | J7: =I7/$I$9 -> 0.12408882 | K7: =SUMIF(Payments!$C$2:$C$49,A7,Payments!$P$2:$P$49) -> 5
A8: Harbourview Events & Hospitality | B8: 44994 | C8: Kochi | D8: IN | E8: Procurement committee | F8: =_xlfn.MINIFS(Payments!$B$2:$B$49,Payments!$C$2:$C$49,A8) -> 45926 | G8: =F8-B8 -> 932 | H8: =COUNTIF(Payments!$C$2:$C$49,A8) -> 1 | I8: =SUMIF(Payments!$C$2:$C$49,A8,Payments!$F$2:$F$49) -> 185000 | J8: =I8/$I$9 -> 0.015832022 | K8: =SUMIF(Payments!$C$2:$C$49,A8,Payments!$P$2:$P$49) -> 0
A9: Total | H9: =SUM(H2:H8) -> 48 | I9: =SUM(I2:I8) -> 11685178 | J9: =SUM(J2:J8) -> 1 | K9: =SUM(K2:K8) -> 44
